celery_bundle/__init__.py
celery_bundle/bundle.py
celery_bundle-2.0.0.dist-info/LICENSE
celery_bundle-2.0.0.dist-info/WHEEL
celery_bundle-2.0.0.dist-info/METADATA
celery_bundle-2.0.0.dist-info/RECORD
